triplesec/__init__.py
triplesec/__main__.py
triplesec/crypto.py
triplesec/utils.py
triplesec/versions.py
TripleSec-0.5.1.dist-info/LICENSE
TripleSec-0.5.1.dist-info/METADATA
TripleSec-0.5.1.dist-info/WHEEL
TripleSec-0.5.1.dist-info/entry_points.txt
TripleSec-0.5.1.dist-info/top_level.txt
TripleSec-0.5.1.dist-info/RECORD
