Metadata-Version: 2.1
Name: TripleSec
Version: 0.5.1
Summary: a Python implementation of TripleSec
Home-page: http://github.com/keybase/python-triplesec
Author: Keybase
Author-email: max@keybase.io
License: BSD-new
Platform: UNKNOWN
Classifier: Intended Audience :: Developers
Classifier: License :: OSI Approved :: BSD License
Classifier: Programming Language :: Python :: 2.6
Classifier: Programming Language :: Python :: 2.7
Classifier: Programming Language :: Python :: 3.3
Classifier: Topic :: Security :: Cryptography
Classifier: Topic :: Software Development :: Libraries
Requires-Dist: pycryptodomex (==3.7.1)
Requires-Dist: scrypt (==0.8.6)
Requires-Dist: six (==1.11.0)
Requires-Dist: pysha3 (==1.0.2)
Requires-Dist: twofish (==0.3.0)
Requires-Dist: salsa20 (==0.3.0)
